tno/quantum/optimization/qubo/__init__.py
tno/quantum/optimization/qubo/py.typed
tno/quantum/optimization/qubo/test/__init__.py
tno/quantum/optimization/qubo/test/test_qubo.py
tno_quantum_optimization_qubo-1.0.1.dist-info/licenses/LICENSE
tno_quantum_optimization_qubo-1.0.1.dist-info/METADATA
tno_quantum_optimization_qubo-1.0.1.dist-info/WHEEL
tno_quantum_optimization_qubo-1.0.1.dist-info/top_level.txt
tno_quantum_optimization_qubo-1.0.1.dist-info/RECORD
