Metadata-Version: 2.4
Name: tno.quantum.optimization.qubo
Version: 1.0.1
Summary: QUBO optimization
Author-email: TNO Quantum Code Lab <tnoquantum@tno.nl>
Maintainer-email: TNO Quantum Code Lab <tnoquantum@tno.nl>
License: Apache License, Version 2.0
Project-URL: Homepage, https://github.com/TNO-Quantum/
Project-URL: Documentation, https://github.com/TNO-Quantum/
Project-URL: Source, https://ci.tno.nl/gitlab/quantum/quantum-applications/quantum-toolbox/microlibs/optimization/microlibs/qubo/qubo
Keywords: QUBO,Quantum,TNO,Optimization
Platform: any
Classifier: License :: OSI Approved :: Apache Software License
Classifier: Programming Language :: Python :: 3
Classifier: Programming Language :: Python :: 3.10
Classifier: Programming Language :: Python :: 3.11
Classifier: Programming Language :: Python :: 3.12
Classifier: Programming Language :: Python :: 3.13
Classifier: Operating System :: OS Independent
Classifier: Intended Audience :: Developers
Classifier: Intended Audience :: Information Technology
Classifier: Intended Audience :: Science/Research
Classifier: Typing :: Typed
Requires-Python: >=3.10
License-File: LICENSE
Requires-Dist: tno.quantum.optimization.qubo.components~=1.0
Requires-Dist: tno.quantum.optimization.qubo.solvers~=1.0
Requires-Dist: tno.quantum.optimization.qubo.preprocessors~=1.0
Requires-Dist: tno.quantum.optimization.qubo.postprocessors~=1.0
Provides-Extra: dwave
Requires-Dist: tno.quantum.optimization.qubo.solvers[dwave]~=1.0; extra == "dwave"
Provides-Extra: qubovert
Requires-Dist: tno.quantum.optimization.qubo.solvers[qubovert]~=1.0; extra == "qubovert"
Provides-Extra: dqo
Requires-Dist: tno.quantum.optimization.qubo.solvers[dqo]~=1.0; extra == "dqo"
Provides-Extra: all
Requires-Dist: tno.quantum.optimization.qubo[dqo,dwave,qubovert]; extra == "all"
Provides-Extra: tests
Requires-Dist: pytest>=8.1.1; extra == "tests"
Requires-Dist: pytest-cov>=4.1.0; extra == "tests"
Requires-Dist: tomlkit; extra == "tests"
Requires-Dist: tno.quantum.optimization.qubo.components[tests]; extra == "tests"
Requires-Dist: tno.quantum.optimization.qubo.solvers[tests]; extra == "tests"
Requires-Dist: tno.quantum.optimization.qubo.preprocessors[tests]; extra == "tests"
Requires-Dist: tno.quantum.optimization.qubo.postprocessors[tests]; extra == "tests"
Provides-Extra: dev
Requires-Dist: tno-dev-utils[default]>=3.3; extra == "dev"
Dynamic: license-file
